igap/__init__.py
igap-0.1.dist-info/METADATA
igap-0.1.dist-info/WHEEL
igap-0.1.dist-info/top_level.txt
igap-0.1.dist-info/RECORD
